LICENSE
MANIFEST.in
README.md
setup.py
itemagic/__init__.py
itemagic/context.py
itemagic/magic.py
itemagic/parser.py
itemagic/spider.py
itemagic/extractors/__init__.py
itemagic/extractors/base.py
itemagic/extractors/const.py
itemagic/extractors/url.py
itemagic/extractors/xpath.py
itemagic/rules/__init__.py
itemagic/rules/base.py
itemagic/rules/const.py
itemagic/rules/map.py
itemagic/rules/url.py
itemagic/rules/xpath.py
scrapy_itemagic.egg-info/PKG-INFO
scrapy_itemagic.egg-info/SOURCES.txt
scrapy_itemagic.egg-info/dependency_links.txt
scrapy_itemagic.egg-info/requires.txt
scrapy_itemagic.egg-info/top_level.txt